{"name":"Cách Thức Cưng Chiều Người Yêu Nhỏ Của Học Bá","folder":"cachthuccungchieunguoiyeunhocuahocba","tacGia":"Quỳnhchaau","theLoai":"Đam Mỹ","trangThai":"Đang ra","description":"Tác giả: Quỳnhchaau<br><br>Thể loại: Hài Hước, Truyện Teen, Đam Mỹ<br><br>Giới thiệu:<br><br>Diệp Lạc từ trước đến nay đều rất yếu ớt, còn có vẻ ngoài xinh đẹp khiến người liên tưởng tới những mỹ nhân thời xưa mong manh, mềm mại.<br><br>Vậy nên Lục Ngôn không thể nào không lo lắng cho được.<br><br>Tưởng tượng cảnh một chàng trai cao 1m89 thâm tình nhìn thiếu niên gầy yếu, khuôn mặt không còn lạnh băng như ngày thường, mà hiện tại tràn ngập khí chất anh trai dịu dàng nhà bên, đôi mắt còn long lanh, tỏ ra uỷ khuất khi bị từ chối, ai mà không động lòng đây???"}