{"name":"Xuyên Qua Thập Niên 70 Gả Cho Con Trai Của Xưởng Trưởng","folder":"xuyenquathapnien70gachocontraicuaxuongtruong","tacGia":"Hảo Tiêu","theLoai":"Ngôn Tình","trangThai":"Đang ra","description":"Ngụy Huyên, một cô gái xuyên không đến một thế giới mới, phải thích nghi với thân phận mới của mình. Tuy nhiên, cuộc đời của cô lại bắt đầu với một hôn nhân khiến cô không hề mong muốn. Ngoài ra, việc bị chôn dưới những lời đồn đại và cảm giác bị xem thường khiến cô càng tìm cách tỏ ra mạnh mẽ và tự tôn hơn. <br><br>Sự xuất hiện của Tưởng Triệt, người chồng tốt giúp cô tìm lại niềm vui và tự tin trong cuộc sống. Sự nghiệp kinh doanh ngày càng phát triển của anh cùng với mối tình sủng ái giữa hai người đã tạo nên một câu chuyện tình cảm đầy cảm động và lãng mạn."}