{"name":"Chờ Ngày Ngắm Biển Cùng Em","folder":"chongayngambiencungem","tacGia":"Tiểu Thần","theLoai":"Ngôn Tình","trangThai":"Full","description":"Trên livestream có người donate cho tôi mười cái du thuyền để tôi gọi cho bạn trai cũ nói tôi nhớ anh ấy.<br><br>Tôi ngập ngừng bấm số.<br><br>Đầu dây bên kia truyền đến một giọng nam khóc nức nở. <br><br>\"Thẩm Tinh Nguyễn, em không có trái tim à, sao giờ em mới nhớ đến anh...\"<br><br>\"Nguyễn Nguyễn, chúng ta quay lại được không?\"<br><br>\"Em không thích anh chỗ nào anh sẽ sửa được không? Đừng không cần anh mà...\".<br><br>Ngay sau đó, phòng phát sóng trực tiếp của tôi như muốn nổ tung.<br><br>Chỉ vì đối phương là một ảnh đế nào đó nổi tiếng với hình tượng cứng rắn, mạnh mẽ."}